<annotation>
	<folder>xml-filer</folder>
	<filename>DSC_0710_compress31.jpg</filename>
	<path>C:\Users\idac1\Documents\DTU\4. Semester\62410 - CDIO-Projekt\xml-filer\DSC_0710_compress31.jpg</path>
	<source>
		<database>Unknown</database>
	</source>
	<size>
		<width>2752</width>
		<height>1548</height>
		<depth>3</depth>
	</size>
	<segmented>0</segmented>
	<object>
		<name>4C</name>
		<pose>Unspecified</pose>
		<truncated>0</truncated>
		<difficult>0</difficult>
		<bndbox>
			<xmin>543</xmin>
			<ymin>484</ymin>
			<xmax>1233</xmax>
			<ymax>1224</ymax>
		</bndbox>
	</object>
	<object>
		<name>6D</name>
		<pose>Unspecified</pose>
		<truncated>0</truncated>
		<difficult>0</difficult>
		<bndbox>
			<xmin>773</xmin>
			<ymin>331</ymin>
			<xmax>1288</xmax>
			<ymax>491</ymax>
		</bndbox>
	</object>
	<object>
		<name>6C</name>
		<pose>Unspecified</pose>
		<truncated>0</truncated>
		<difficult>0</difficult>
		<bndbox>
			<xmin>698</xmin>
			<ymin>135</ymin>
			<xmax>1220</xmax>
			<ymax>330</ymax>
		</bndbox>
	</object>
	<object>
		<name>QC</name>
		<pose>Unspecified</pose>
		<truncated>0</truncated>
		<difficult>0</difficult>
		<bndbox>
			<xmin>1551</xmin>
			<ymin>625</ymin>
			<xmax>2263</xmax>
			<ymax>1509</ymax>
		</bndbox>
	</object>
	<object>
		<name>QH</name>
		<pose>Unspecified</pose>
		<truncated>0</truncated>
		<difficult>0</difficult>
		<bndbox>
			<xmin>1551</xmin>
			<ymin>383</ymin>
			<xmax>2044</xmax>
			<ymax>643</ymax>
		</bndbox>
	</object>
	<object>
		<name>10S</name>
		<pose>Unspecified</pose>
		<truncated>0</truncated>
		<difficult>0</difficult>
		<bndbox>
			<xmin>1461</xmin>
			<ymin>200</ymin>
			<xmax>2004</xmax>
			<ymax>452</ymax>
		</bndbox>
	</object>
	<object>
		<name>AC</name>
		<pose>Unspecified</pose>
		<truncated>0</truncated>
		<difficult>0</difficult>
		<bndbox>
			<xmin>1399</xmin>
			<ymin>26</ymin>
			<xmax>1950</xmax>
			<ymax>262</ymax>
		</bndbox>
	</object>
</annotation>
