<annotation>
	<folder>Billeder af kort - under 200KB</folder>
	<filename>IMG_8995.jpg</filename>
	<path>C:\Users\Cecilie\OneDrive\Documents\CDIO\Billeder af kort - under 200KB\IMG_8995.jpg</path>
	<source>
		<database>Unknown</database>
	</source>
	<size>
		<width>1024</width>
		<height>768</height>
		<depth>3</depth>
	</size>
	<segmented>0</segmented>
	<object>
		<name>7H</name>
		<pose>Unspecified</pose>
		<truncated>0</truncated>
		<difficult>0</difficult>
		<bndbox>
			<xmin>425</xmin>
			<ymin>158</ymin>
			<xmax>811</xmax>
			<ymax>465</ymax>
		</bndbox>
	</object>
	<object>
		<name>7S</name>
		<pose>Unspecified</pose>
		<truncated>0</truncated>
		<difficult>0</difficult>
		<bndbox>
			<xmin>190</xmin>
			<ymin>92</ymin>
			<xmax>423</xmax>
			<ymax>478</ymax>
		</bndbox>
	</object>
</annotation>
