<annotation>
	<folder>img</folder>
	<filename>IMG_20200609_121500.jpg</filename>
	<path>C:\Users\Christoffer\Desktop\img\IMG_20200609_121500.jpg</path>
	<source>
		<database>Unknown</database>
	</source>
	<size>
		<width>992</width>
		<height>744</height>
		<depth>3</depth>
	</size>
	<segmented>0</segmented>
	<object>
		<name>QC</name>
		<pose>Unspecified</pose>
		<truncated>0</truncated>
		<difficult>0</difficult>
		<bndbox>
			<xmin>130</xmin>
			<ymin>116</ymin>
			<xmax>355</xmax>
			<ymax>388</ymax>
		</bndbox>
	</object>
	<object>
		<name>5H</name>
		<pose>Unspecified</pose>
		<truncated>0</truncated>
		<difficult>0</difficult>
		<bndbox>
			<xmin>126</xmin>
			<ymin>27</ymin>
			<xmax>321</xmax>
			<ymax>114</ymax>
		</bndbox>
	</object>
	<object>
		<name>KS</name>
		<pose>Unspecified</pose>
		<truncated>0</truncated>
		<difficult>0</difficult>
		<bndbox>
			<xmin>456</xmin>
			<ymin>135</ymin>
			<xmax>682</xmax>
			<ymax>392</ymax>
		</bndbox>
	</object>
	<object>
		<name>QD</name>
		<pose>Unspecified</pose>
		<truncated>0</truncated>
		<difficult>0</difficult>
		<bndbox>
			<xmin>450</xmin>
			<ymin>53</ymin>
			<xmax>636</xmax>
			<ymax>133</ymax>
		</bndbox>
	</object>
	<object>
		<name>3D</name>
		<pose>Unspecified</pose>
		<truncated>0</truncated>
		<difficult>0</difficult>
		<bndbox>
			<xmin>712</xmin>
			<ymin>128</ymin>
			<xmax>916</xmax>
			<ymax>394</ymax>
		</bndbox>
	</object>
	<object>
		<name>9D</name>
		<pose>Unspecified</pose>
		<truncated>0</truncated>
		<difficult>0</difficult>
		<bndbox>
			<xmin>685</xmin>
			<ymin>57</ymin>
			<xmax>864</xmax>
			<ymax>128</ymax>
		</bndbox>
	</object>
	<object>
		<name>BACK</name>
		<pose>Unspecified</pose>
		<truncated>0</truncated>
		<difficult>0</difficult>
		<bndbox>
			<xmin>502</xmin>
			<ymin>405</ymin>
			<xmax>749</xmax>
			<ymax>728</ymax>
		</bndbox>
	</object>
</annotation>
