<annotation>
	<folder>img</folder>
	<filename>IMG_20200609_121530.jpg</filename>
	<path>C:\Users\Christoffer\Desktop\img\IMG_20200609_121530.jpg</path>
	<source>
		<database>Unknown</database>
	</source>
	<size>
		<width>992</width>
		<height>744</height>
		<depth>3</depth>
	</size>
	<segmented>0</segmented>
	<object>
		<name>BACK</name>
		<pose>Unspecified</pose>
		<truncated>0</truncated>
		<difficult>0</difficult>
		<bndbox>
			<xmin>214</xmin>
			<ymin>107</ymin>
			<xmax>395</xmax>
			<ymax>181</ymax>
		</bndbox>
	</object>
	<object>
		<name>BACK</name>
		<pose>Unspecified</pose>
		<truncated>0</truncated>
		<difficult>0</difficult>
		<bndbox>
			<xmin>204</xmin>
			<ymin>185</ymin>
			<xmax>397</xmax>
			<ymax>284</ymax>
		</bndbox>
	</object>
	<object>
		<name>BACK</name>
		<pose>Unspecified</pose>
		<truncated>0</truncated>
		<difficult>0</difficult>
		<bndbox>
			<xmin>705</xmin>
			<ymin>248</ymin>
			<xmax>937</xmax>
			<ymax>520</ymax>
		</bndbox>
	</object>
	<object>
		<name>BACK</name>
		<pose>Unspecified</pose>
		<truncated>0</truncated>
		<difficult>0</difficult>
		<bndbox>
			<xmin>710</xmin>
			<ymin>183</ymin>
			<xmax>891</xmax>
			<ymax>252</ymax>
		</bndbox>
	</object>
	<object>
		<name>BACK</name>
		<pose>Unspecified</pose>
		<truncated>0</truncated>
		<difficult>0</difficult>
		<bndbox>
			<xmin>697</xmin>
			<ymin>121</ymin>
			<xmax>871</xmax>
			<ymax>188</ymax>
		</bndbox>
	</object>
	<object>
		<name>7C</name>
		<pose>Unspecified</pose>
		<truncated>0</truncated>
		<difficult>0</difficult>
		<bndbox>
			<xmin>205</xmin>
			<ymin>276</ymin>
			<xmax>405</xmax>
			<ymax>567</ymax>
		</bndbox>
	</object>
	<object>
		<name>10C</name>
		<pose>Unspecified</pose>
		<truncated>0</truncated>
		<difficult>0</difficult>
		<bndbox>
			<xmin>469</xmin>
			<ymin>285</ymin>
			<xmax>685</xmax>
			<ymax>569</ymax>
		</bndbox>
	</object>
	<object>
		<name>3C</name>
		<pose>Unspecified</pose>
		<truncated>0</truncated>
		<difficult>0</difficult>
		<bndbox>
			<xmin>473</xmin>
			<ymin>183</ymin>
			<xmax>655</xmax>
			<ymax>291</ymax>
		</bndbox>
	</object>
	<object>
		<name>7H</name>
		<pose>Unspecified</pose>
		<truncated>0</truncated>
		<difficult>0</difficult>
		<bndbox>
			<xmin>471</xmin>
			<ymin>128</ymin>
			<xmax>647</xmax>
			<ymax>181</ymax>
		</bndbox>
	</object>
</annotation>
